<?xml version="1.0" encoding="utf-8" ?>
<G21>
	<nodes>
		<node>
		<name>1</name>
		</node>
		<node>
		<name>2</name>
		</node>
		<node>
		<name>3</name>
		</node>
		<node>
		<name>4</name>
		</node>
		<node>
		<name>5</name>
		</node>
		<node>
		<name>6</name>
		</node>
	</nodes>
	<lines>
		<line>
		<name>e1</name>
		<begin>1</begin>
		<end>2</end>
		</line>
		<line>
		<name>e2</name>
		<begin>1</begin>
		<end>6</end>
		</line>
		<line>
		<name>e3</name>
		<begin>3</begin>
		<end>2</end>
		</line>
		<line>
		<name>e4</name>
		<begin>3</begin>
		<end>4</end>
		</line>
		<line>
		<name>e5</name>
		<begin>3</begin>
		<end>6</end>
		</line>
		<line>
		<name>e6</name>
		<begin>5</begin>
		<end>6</end>
		</line>
		<line>
		<name>e7</name>
		<begin>3</begin>
		<end>2</end>
		</line>
	</lines>
</G21>
